cenaming/__init__.py
cenaming/_version.py
cenaming/name_shortener.py
cenaming/us_states.py
cenaming-1.0.2.dist-info/DESCRIPTION.rst
cenaming-1.0.2.dist-info/METADATA
cenaming-1.0.2.dist-info/RECORD
cenaming-1.0.2.dist-info/WHEEL
cenaming-1.0.2.dist-info/metadata.json
cenaming-1.0.2.dist-info/top_level.txt
