Metadata-Version: 2.0
Name: cenaming
Version: 1.0.2
Summary: Company legal name normalization and shortening.
Home-page: https://github.com/portfoliome/cenaming
Author: Philip Martin
Author-email: philip.martin@censible.co
License: MIT
Keywords: companies finance names
Platform: UNKNOWN
Classifier: Development Status :: 5 - Production/Stable
Classifier: Intended Audience :: Developers
Classifier: Natural Language :: English
Classifier: Programming Language :: Python :: 3.5
Classifier: Topic :: Utilities
Provides-Extra: develop
Requires-Dist: flake8; extra == 'develop'
Requires-Dist: pylint; extra == 'develop'
Provides-Extra: test
Requires-Dist: pytest; extra == 'test'
Requires-Dist: pytest-cov; extra == 'test'
